README.md
setup.py
./ncnn/__init__.py
./ncnn/ncnn.cpython-311-riscv64-linux-gnu.so
./ncnn/model_zoo/__init__.py
./ncnn/model_zoo/fasterrcnn.py
./ncnn/model_zoo/mobilenetssd.py
./ncnn/model_zoo/mobilenetv2ssdlite.py
./ncnn/model_zoo/mobilenetv3ssdlite.py
./ncnn/model_zoo/model_store.py
./ncnn/model_zoo/model_zoo.py
./ncnn/model_zoo/nanodet.py
./ncnn/model_zoo/peleenetssd.py
./ncnn/model_zoo/retinaface.py
./ncnn/model_zoo/rfcn.py
./ncnn/model_zoo/shufflenetv2.py
./ncnn/model_zoo/simplepose.py
./ncnn/model_zoo/squeezenet.py
./ncnn/model_zoo/squeezenetssd.py
./ncnn/model_zoo/yolact.py
./ncnn/model_zoo/yolov2.py
./ncnn/model_zoo/yolov3.py
./ncnn/model_zoo/yolov4.py
./ncnn/model_zoo/yolov5.py
./ncnn/model_zoo/yolov7.py
./ncnn/model_zoo/yolov8.py
./ncnn/utils/__init__.py
./ncnn/utils/download.py
./ncnn/utils/functional.py
./ncnn/utils/objects.py
./ncnn/utils/visual.py
ncnn_riscv_wheel.egg-info/PKG-INFO
ncnn_riscv_wheel.egg-info/SOURCES.txt
ncnn_riscv_wheel.egg-info/dependency_links.txt
ncnn_riscv_wheel.egg-info/requires.txt
ncnn_riscv_wheel.egg-info/top_level.txt
tests/test_allocator.py
tests/test_blob.py
tests/test_extractor.py
tests/test_mat.py
tests/test_net.py
tests/test_option.py
tests/test_paramdict.py
tests/test_vulkan_allocator.py
tests/test_vulkan_device.py