Metadata-Version: 2.1
Name: ncnn-riscv-wheel
Version: 1.0.20240706
Summary: ncnn is a high-performance neural network inference framework optimized for the mobile platform
Home-page: https://github.com/per1cycle/ncnn-riscv-wheel
Author: nihui
Author-email: nihuini@tencent.com
Maintainer: per1cycle
Maintainer-email: pericycle.cc@gmail.com
License: BSD-3
Classifier: Programming Language :: C++
Classifier: Programming Language :: Python :: 3
Classifier: Programming Language :: Python :: 3.6
Classifier: Programming Language :: Python :: 3.7
Classifier: Programming Language :: Python :: 3.8
Classifier: Programming Language :: Python :: 3.9
Classifier: Programming Language :: Python :: 3.10
Classifier: License :: OSI Approved :: BSD License
Classifier: Operating System :: OS Independent
Requires-Python: >=3.5
